django_oscar_wagtail-0.1.2.dist-info/DESCRIPTION.rst
django_oscar_wagtail-0.1.2.dist-info/METADATA
django_oscar_wagtail-0.1.2.dist-info/RECORD
django_oscar_wagtail-0.1.2.dist-info/WHEEL
django_oscar_wagtail-0.1.2.dist-info/metadata.json
django_oscar_wagtail-0.1.2.dist-info/top_level.txt
oscar_wagtail/__init__.py
oscar_wagtail/abstract_models.py
oscar_wagtail/app.py
oscar_wagtail/blocks.py
oscar_wagtail/edit_handlers.py
oscar_wagtail/models.py
oscar_wagtail/urls.py
oscar_wagtail/views.py
oscar_wagtail/wagtail_hooks.py
oscar_wagtail/widgets.py
oscar_wagtail/migrations/0001_initial.py
oscar_wagtail/migrations/__init__.py
oscar_wagtail/static/oscar_wagtail/js/product-chooser.js
oscar_wagtail/templates/oscar_wagtail/blocks/product.html
oscar_wagtail/templates/oscar_wagtail/chooser/product_choose.html
oscar_wagtail/templates/oscar_wagtail/chooser/product_choose.js
oscar_wagtail/templates/oscar_wagtail/chooser/product_chosen.js
oscar_wagtail/templates/oscar_wagtail/chooser/product_results.html
oscar_wagtail/templates/oscar_wagtail/widgets/product_chooser.html
