Metadata-Version: 2.0
Name: django-oscar-wagtail
Version: 0.1.2
Summary: Integration between Django Oscar and Wagtail
Home-page: UNKNOWN
Author: Michael van Tellingen
Author-email: michaelvantellingen@gmail.com
License: MIT
Platform: UNKNOWN
Classifier: Development Status :: 2 - Pre-Alpha
Classifier: License :: OSI Approved :: MIT License
Classifier: Programming Language :: Python :: 2
Classifier: Programming Language :: Python :: 2.7
Classifier: Programming Language :: Python :: 3
Classifier: Programming Language :: Python :: 3.3
Classifier: Programming Language :: Python :: 3.4
Classifier: Programming Language :: Python :: 3.5
Classifier: Programming Language :: Python :: Implementation :: CPython
Classifier: Programming Language :: Python :: Implementation :: PyPy
Requires-Dist: django-oscar (>=1.3.0)
Requires-Dist: wagtail (>=1.6.0)
Provides-Extra: docs
Requires-Dist: sphinx (>=1.4.0); extra == 'docs'
Provides-Extra: test
Requires-Dist: pytest-cov (==2.3.1); extra == 'test'
Requires-Dist: pytest-django (==3.0.0); extra == 'test'
Requires-Dist: pytest-pythonpath (==0.7); extra == 'test'
Requires-Dist: pytest (==3.0.0); extra == 'test'
Requires-Dist: isort (==4.2.5); extra == 'test'
Requires-Dist: flake8 (==3.0.3); extra == 'test'
Requires-Dist: flake8-blind-except (==0.1.1); extra == 'test'
Requires-Dist: flake8-debugger (==1.4.0); extra == 'test'
